{"logtostderr": false, "alsologtostderr": false, "log_dir": "", "v": 0, "verbosity": 0, "logger_levels": {}, "stderrthreshold": "fatal", "showprefixforinfo": true, "run_with_pdb": false, "pdb_post_mortem": false, "pdb": false, "run_with_profiling": false, "profile_file": null, "use_cprofile_for_profiling": true, "only_check_args": false, "results_path": "cyberbach_songs", "song_name": "", "use_timidity": true, "dataset": "MuseData", "subset": "train", "index": 0, "model_path": "cyberbach_models/tanh_limitcycle", "length": 200, "max_on_notes": 10, "min_on_notes": 0, "noise_variance": 0.05, "?": false, "help": false, "helpshort": false, "helpfull": false, "helpxml": false}